web3_data_center/__init__.py
web3_data_center/clients/__init__.py
web3_data_center/clients/base_client.py
web3_data_center/clients/api/base_api_client.py
web3_data_center/clients/api/endpoint_config.py
web3_data_center/clients/api/etherscan_client.py
web3_data_center/clients/api/funding_client.py
web3_data_center/clients/api/fwalert_client.py
web3_data_center/clients/api/x_monitor_client.py
web3_data_center/clients/batch/__init__.py
web3_data_center/clients/batch/controller.py
web3_data_center/clients/batch/executor.py
web3_data_center/clients/batch/types.py
web3_data_center/clients/database/base_database_client.py
web3_data_center/clients/database/block_opensearch_client.py
web3_data_center/clients/database/neo4j_client.py
web3_data_center/clients/database/opensearch_client.py
web3_data_center/clients/database/pg_client.py
web3_data_center/clients/database/web3_label_client.py
web3_data_center/clients/mixins/__init__.py
web3_data_center/clients/mixins/auth.py
web3_data_center/clients/mixins/config.py
web3_data_center/clients/mixins/connection.py
web3_data_center/clients/mixins/operation_modes.py
web3_data_center/clients/mixins/rate_limit.py
web3_data_center/clients/wrapper/__init__.py
web3_data_center/clients/wrapper/base_wrapper_client.py
web3_data_center/clients/wrapper/web3_client.py
web3_data_center/core/__init__.py
web3_data_center/core/data_center.py
web3_data_center/core/data_center_bak.py
web3_data_center/models/__init__.py
web3_data_center/models/holder.py
web3_data_center/models/orders.py
web3_data_center/models/pair.py
web3_data_center/models/price_history_point.py
web3_data_center/models/source.py
web3_data_center/models/token.py
web3_data_center/models/token_security.py
web3_data_center/models/transaction.py
web3_data_center/utils/__init__.py
web3_data_center/utils/cache.py
web3_data_center/utils/content_extractor.py
web3_data_center/utils/database.py
web3_data_center/utils/logger.py
web3_data_center/utils/rate_limiter.py
web3_data_center-0.9.8.dist-info/METADATA
web3_data_center-0.9.8.dist-info/WHEEL
web3_data_center-0.9.8.dist-info/top_level.txt
web3_data_center-0.9.8.dist-info/RECORD
