Metadata-Version: 2.4
Name: web3_data_center
Version: 0.9.8
Summary: Web3 data center integrating multiple APIs for blockchain data analysis
Home-page: https://github.com/gmatrixuniverse/web3_data_center
Author: Gmatrixuniverse
Author-email: gmatrixuniverse@gmail.com
Keywords: web3 blockchain data analysis
Classifier: Development Status :: 3 - Alpha
Classifier: Intended Audience :: Developers
Classifier: Topic :: Software Development :: Libraries :: Python Modules
Classifier: License :: OSI Approved :: MIT License
Classifier: Programming Language :: Python :: 3
Classifier: Programming Language :: Python :: 3.7
Classifier: Programming Language :: Python :: 3.8
Classifier: Programming Language :: Python :: 3.9
Classifier: Programming Language :: Python :: 3.10
Requires-Python: >=3.7
Requires-Dist: asyncio
Requires-Dist: aiohttp
Requires-Dist: opensearch-py
Requires-Dist: psycopg2-binary
Requires-Dist: beautifulsoup4
Requires-Dist: pytesseract
Requires-Dist: Pillow
Requires-Dist: python-dotenv
Requires-Dist: evm-decoder>=0.3.4
Dynamic: author
Dynamic: author-email
Dynamic: classifier
Dynamic: description
Dynamic: description-content-type
Dynamic: home-page
Dynamic: keywords
Dynamic: requires-dist
Dynamic: requires-python
Dynamic: summary
